slides_viewer/__init__.py
slides_viewer/args.py
slides_viewer/console.py
slides_viewer/player/AnimationVideo.py
slides_viewer/player/Application.py
slides_viewer/player/Player.py
slides_viewer/player/Window.py
slides_viewer/player/__init__.py
slides_viewer/playlist/Animation.py
slides_viewer/playlist/Playlist.py
slides_viewer/playlist/PlaylistJSON.py
slides_viewer/playlist/Slide.py
slides_viewer/playlist/__init__.py
slides_viewer-1.0.0.dist-info/entry_points.txt
slides_viewer-1.0.0.dist-info/LICENSE
slides_viewer-1.0.0.dist-info/WHEEL
slides_viewer-1.0.0.dist-info/METADATA
slides_viewer-1.0.0.dist-info/RECORD
